{
    "type": "full",
    "name": "6. neděle v mezidobí C",
    "year": "C",
    "parts": [
        {
            "title": "Vstupní zpěv",
            "songs": [
                {
                    "page": "195",
                    "melody": "89d",
                    "link": "mezidobi_04_A"
                }
            ]
        },
        {
            "title": "Zpěv po prvním čtení",
            "songs": [
                {
                    "response": "49",
                    "links": [
                        {
                            "filename": "Ps001_02",
                            "kb_page": "9"
                        }
                    ]
                }
            ]
        },
        {
            "title": "Zpěv před evangeliem",
            "songs": [
                {
                    "page": "196",
                    "melody": "98i",
                    "link": "mezidobi_04_A"
                }
            ]
        },
        {
            "title": "Zpěv k přípravě darů",
            "songs": [
                {
                    "page": "197",
                    "melody": "78a",
                    "link": "mezidobi_04_A"
                }
            ]
        },
        {
            "title": "Zpěv k přijímání",
            "songs": [
                {
                    "page": "198",
                    "melody": "36j",
                    "link": "mezidobi_04_A"
                }
            ]
        }
    ]
}